pubmed_paper_fetcher/__init__.py
pubmed_paper_fetcher/cli.py
pubmed_paper_fetcher/fetcher.py
pubmed_paper_fetcher-0.1.0.dist-info/METADATA
pubmed_paper_fetcher-0.1.0.dist-info/WHEEL
pubmed_paper_fetcher-0.1.0.dist-info/top_level.txt
pubmed_paper_fetcher-0.1.0.dist-info/RECORD
