Metadata-Version: 2.4
Name: pubmed-paper-fetcher
Version: 0.1.0
Summary: Fetch and filter PubMed papers based on pharmaceutical/biotech affiliations.
Home-page: https://github.com/supriya357/pubmed-paper-fetcher
Author: Akkala Supriya
Author-email: akkalasupriya3@gmail.com
Classifier: Programming Language :: Python :: 3
Classifier: Operating System :: OS Independent
Requires-Python: >=3.6
Requires-Dist: biopython
Dynamic: author
Dynamic: author-email
Dynamic: classifier
Dynamic: description
Dynamic: description-content-type
Dynamic: home-page
Dynamic: requires-dist
Dynamic: requires-python
Dynamic: summary
